card_generator/__init__.py
card_generator/bin-list-data.csv
card_generator/card_generator.py
card_generator/card_validator.py
card_generator/config.py
card_generator-0.1.6.dist-info/licenses/LICENSE
tests/test_card_generator.py
tests/test_card_validator.py
card_generator-0.1.6.dist-info/METADATA
card_generator-0.1.6.dist-info/WHEEL
card_generator-0.1.6.dist-info/top_level.txt
card_generator-0.1.6.dist-info/RECORD
