Metadata-Version: 2.4
Name: card_generator
Version: 0.1.6
Summary: A library to generate and validate credit card numbers with local BIN lookup.
Author-email: NjProVk <njprovk@gmail.com>
Project-URL: Homepage, https://github.com/NjProVk/CreditsCardTools
Project-URL: Bug Tracker, https://github.com/NjProVk/CreditsCardTools/issues
Keywords: credit card,card generator,card validator,luhn,luhn algorithm,bin,bin lookup,bin checker,iin,generate,generator,validate,validator,validation,visa,mastercard,amex,discover,fintech,payment,ecommerce,test data,mock data,fake data,offline,no-api,local-database
Classifier: Development Status :: 4 - Beta
Classifier: Intended Audience :: Developers
Classifier: Operating System :: OS Independent
Classifier: License :: OSI Approved :: Apache Software License
Classifier: Programming Language :: Python :: 3
Classifier: Programming Language :: Python :: 3.8
Classifier: Programming Language :: Python :: 3.9
Classifier: Programming Language :: Python :: 3.10
Classifier: Programming Language :: Python :: 3.11
Classifier: Programming Language :: Python :: 3.12
Classifier: Programming Language :: Python :: 3.13
Classifier: Topic :: Software Development :: Libraries :: Python Modules
Classifier: Topic :: Utilities
Requires-Python: >=3.8
License-File: LICENSE
Dynamic: license-file
